pangram/__init__.py
pangram/text_classifier.py
pangram_sdk-0.1.11.dist-info/METADATA
pangram_sdk-0.1.11.dist-info/WHEEL
pangram_sdk-0.1.11.dist-info/licenses/LICENSE
pangram_sdk-0.1.11.dist-info/RECORD
