Metadata-Version: 2.4
Name: pangram-sdk
Version: 0.1.11
Summary: 
License-File: LICENSE
Author: Max Spero
Author-email: max@pangramlabs.com
Requires-Python: >=3.9,<4.0
Classifier: Programming Language :: Python :: 3
Classifier: Programming Language :: Python :: 3.9
Classifier: Programming Language :: Python :: 3.10
Classifier: Programming Language :: Python :: 3.11
Classifier: Programming Language :: Python :: 3.12
Classifier: Programming Language :: Python :: 3.13
Classifier: Programming Language :: Python :: 3.14
Requires-Dist: requests (>=2.32.0,<3.0.0)
Requires-Dist: urllib3 (>=2.3.0)
